{
  "snapshot": {
    "created": "2024-10-24T15:12:26.186",
    "database": {
      "productVersion": "14.13",
      "shortName": "postgresql",
      "majorVersion": "14",
      "minorVersion": "13",
      "user": "postgres",
      "productName": "PostgreSQL",
      "url": "jdbc:postgresql://localhost:5433/x15_prod_au_replica"
    },
    "objects": {
      "liquibase.structure.core.Catalog": [
        {
          "catalog": {
            "default": true,
            "name": "x15_prod_au_replica",
            "snapshotId": "9aa1100"
          }
        }
      ]
      ,
      "liquibase.structure.core.Schema": [
        {
          "schema": {
            "catalog": "liquibase.structure.core.Catalog#9aa1100",
            "name": "pg_catalog",
            "snapshotId": "9aa1101"
          }
        }
      ]
      
    },
    "snapshotControl": {
      "snapshotControl": {
        "includedType": [
          "liquibase.structure.core.Catalog",
          "liquibase.structure.core.Column",
          "liquibase.structure.core.ForeignKey",
          "liquibase.structure.core.Index",
          "liquibase.structure.core.PrimaryKey",
          "liquibase.structure.core.Schema",
          "liquibase.structure.core.Sequence",
          "liquibase.structure.core.Table",
          "liquibase.structure.core.UniqueConstraint",
          "liquibase.structure.core.View"
        ]
        
      }
    }
  }
}
